pywe_storage/__init__.py
pywe_storage/basestorage.py
pywe_storage/memcachedstorage.py
pywe_storage/memorystorage.py
pywe_storage/redisstorage.py
pywe_storage/shovestorage.py
pywe_storage-1.0.1.dist-info/DESCRIPTION.rst
pywe_storage-1.0.1.dist-info/METADATA
pywe_storage-1.0.1.dist-info/RECORD
pywe_storage-1.0.1.dist-info/WHEEL
pywe_storage-1.0.1.dist-info/metadata.json
pywe_storage-1.0.1.dist-info/top_level.txt
